{"Young hero saving lives": {"type": "Full text", "pg": {"ts_rank": [], "ts_rank_cd": []}, "pyluc": {"BM25": [{"rank": 5.0493550300598145, "title": "Super Drags", "description": "In this adult animated series, three gay co-workers lead double lives as drag queen superheroes, sav"}, {"rank": 4.981884002685547, "title": "Danger Mouse", "description": "Danger Mouse is back saving London, saving the World and, most importantly, saving Penfold in brand "}, {"rank": 4.278811931610107, "title": "The Man Who Feels No Pain", "description": "Leveraging his ability to withstand pain, a young man trains to follow in the footsteps of his marti"}, {"rank": 4.1174516677856445, "title": "Kid Cosmic", "description": "A young boy who dreams of becoming a hero, stumbles across some cosmic stones of power. His dreams a"}, {"rank": 3.698969841003418, "title": "Chickenhare and the Hamster of Darkness", "description": "Follows a young hero born half chicken and half hare. Eager to fit in and feel loved in spite of his"}, {"rank": 3.6576640605926514, "title": "Trotro", "description": "Trotro is a little donkey with a head full of ideas. He knows exactly what he likes and doesn't like"}, {"rank": 3.455913782119751, "title": "Adventure Beast", "description": "A brave zoologist, his spunky niece and anxious assistant explore the world while saving wild beasts"}, {"rank": 3.394700527191162, "title": "Teen Mom 2", "description": "Jenelle, Chelsea, Kailyn, and Leah are four young women navigating complicated lives. It's not alway"}, {"rank": 3.3470139503479004, "title": "Major", "description": "Based on the life of real-life Hero Major Sandeep Unnikrishnan, Major, the film, aims to show how th"}, {"rank": 3.332047939300537, "title": "Jarhead: Law of Return", "description": "Major Ronan Jackson, an accomplished fighter pilot for the Israel Defense Forces and son of a U.S. S"}], "TF-IDF": [{"rank": 2.685877799987793, "title": "Danger Mouse", "description": "Danger Mouse is back saving London, saving the World and, most importantly, saving Penfold in brand "}, {"rank": 2.332395553588867, "title": "Super Drags", "description": "In this adult animated series, three gay co-workers lead double lives as drag queen superheroes, sav"}, {"rank": 2.1274728775024414, "title": "The Man Who Feels No Pain", "description": "Leveraging his ability to withstand pain, a young man trains to follow in the footsteps of his marti"}, {"rank": 1.9838786125183105, "title": "Kid Cosmic", "description": "A young boy who dreams of becoming a hero, stumbles across some cosmic stones of power. His dreams a"}, {"rank": 1.9538919925689697, "title": "I Am the Pretty Thing That Lives in the House", "description": "A young nurse takes care of elderly author who lives in a haunted house."}, {"rank": 1.9495073556900024, "title": "Teen Mom 2", "description": "Jenelle, Chelsea, Kailyn, and Leah are four young women navigating complicated lives. It's not alway"}, {"rank": 1.7731280326843262, "title": "The Next Step", "description": "Follow the lives of an elite group of young dancers who train at The Next Step Studio."}, {"rank": 1.681915044784546, "title": "Chickenhare and the Hamster of Darkness", "description": "Follows a young hero born half chicken and half hare. Eager to fit in and feel loved in spite of his"}, {"rank": 1.6562354564666748, "title": "Trotro", "description": "Trotro is a little donkey with a head full of ideas. He knows exactly what he likes and doesn't like"}, {"rank": 1.595346212387085, "title": "Jab We Met", "description": "A depressed wealthy businessman and a spunky and care-free young woman embark on an unexpected journ"}]}, "wo": {"BM25": [{"rank": 14.08702165806346, "title": "We Can Be Heroes", "description": "When alien invaders capture Earth's superheroes, their kids must learn to work together to save thei"}, {"rank": 13.673483617773357, "title": "Modest Heroes", "description": "Two tiny, aquatic humanoids search for their missing father, a boy battles a lethal allergy to eggs,"}, {"rank": 13.026899188054994, "title": "Too Young The Hero", "description": "TV movie based upon the true story of Calvin Graham, who, as a 12 year old boy, enlisted in the US N"}, {"rank": 13.005446305270027, "title": "Monster Hunter: Legends of the Guild", "description": "In a world where humans and fearsome monsters live in an uneasy balance, young hunter Aiden fights t"}, {"rank": 12.98015905964112, "title": "I Am the Pretty Thing That Lives in the House", "description": "A young nurse takes care of elderly author who lives in a haunted house."}, {"rank": 12.373058199751153, "title": "Heroes of Goo Jit Zu", "description": "Three Super Hero Animals Who Get Hit With Goo In The Sky Then Get Awsome Powers."}, {"rank": 11.928269095564241, "title": "Major", "description": "Based on the life of real-life Hero Major Sandeep Unnikrishnan, Major, the film, aims to show how th"}, {"rank": 11.518334288160606, "title": "Super Monsters Save Halloween", "description": "It's Halloween in Pitchfork Pines, but the neighbors don't seem to be in the mood. Can the Super Mon"}, {"rank": 11.479883366788002, "title": "The Young Messiah", "description": "Tells the story of Jesus Christ at age seven as he and his family depart Egypt to return home to Naz"}, {"rank": 11.217771240534585, "title": "StarBeam: Halloween Hero", "description": "Greedy Captain Fishbeard is stealing everybody's Halloween treats for himself, but StarBeam and Boos"}], "TF-IDF": [{"rank": 14.08702165806346, "title": "We Can Be Heroes", "description": "When alien invaders capture Earth's superheroes, their kids must learn to work together to save thei"}, {"rank": 13.673483617773357, "title": "Modest Heroes", "description": "Two tiny, aquatic humanoids search for their missing father, a boy battles a lethal allergy to eggs,"}, {"rank": 13.026899188054994, "title": "Too Young The Hero", "description": "TV movie based upon the true story of Calvin Graham, who, as a 12 year old boy, enlisted in the US N"}, {"rank": 13.005446305270027, "title": "Monster Hunter: Legends of the Guild", "description": "In a world where humans and fearsome monsters live in an uneasy balance, young hunter Aiden fights t"}, {"rank": 12.98015905964112, "title": "I Am the Pretty Thing That Lives in the House", "description": "A young nurse takes care of elderly author who lives in a haunted house."}, {"rank": 12.373058199751153, "title": "Heroes of Goo Jit Zu", "description": "Three Super Hero Animals Who Get Hit With Goo In The Sky Then Get Awsome Powers."}, {"rank": 11.928269095564241, "title": "Major", "description": "Based on the life of real-life Hero Major Sandeep Unnikrishnan, Major, the film, aims to show how th"}, {"rank": 11.518334288160606, "title": "Super Monsters Save Halloween", "description": "It's Halloween in Pitchfork Pines, but the neighbors don't seem to be in the mood. Can the Super Mon"}, {"rank": 11.479883366788002, "title": "The Young Messiah", "description": "Tells the story of Jesus Christ at age seven as he and his family depart Egypt to return home to Naz"}, {"rank": 11.217771240534585, "title": "StarBeam: Halloween Hero", "description": "Greedy Captain Fishbeard is stealing everybody's Halloween treats for himself, but StarBeam and Boos"}]}}}